danya/__init__.py
danya/chat.py
danya/login.py
danya/main.py
danya/search.py
danya/data/artyom_c.txt
danya/data/artyom_d.txt
danya/data/artyom_dl.txt
danya/data/artyom_t.txt
danya/data/danya_c.txt
danya/data/danya_d.txt
danya/data/danya_t.txt
danya/data/misha_c.txt
danya/data/misha_d.txt
danya/data/misha_dl.txt
danya/data/theory_c.txt
danya/data/theory_t.txt
danya-1.0.0.dist-info/METADATA
danya-1.0.0.dist-info/WHEEL
danya-1.0.0.dist-info/top_level.txt
danya-1.0.0.dist-info/RECORD
