Metadata-Version: 2.4
Name: danya
Version: 1.0.0
Summary: Катаем всё!
Requires-Python: >=3.6
Dynamic: requires-python
Dynamic: summary
